pysumix/__init__.py
pysumix/demosaic.py
pysumix/rgb2gray.py
pysumix-0.6.0.dist-info/METADATA
pysumix-0.6.0.dist-info/RECORD
pysumix-0.6.0.dist-info/WHEEL
pysumix-0.6.0.dist-info/top_level.txt
