Metadata-Version: 2.1
Name: pysumix
Version: 0.6.0
Summary: Sumix SMX API and data writing and live display
Home-page: https://github.com/scivision/pysumix
Author: Michael Hirsch, Ph.D.
License: UNKNOWN
Platform: UNKNOWN
Classifier: Development Status :: 4 - Beta
Classifier: Environment :: Console
Classifier: Intended Audience :: Science/Research
Classifier: Operating System :: OS Independent
Classifier: Programming Language :: Python :: 3.6
Classifier: Programming Language :: Python :: 3.7
Classifier: Topic :: Scientific/Engineering :: Medical Science Apps.
Requires-Python: >=3.6
Provides-Extra: plot
Provides-Extra: io
Provides-Extra: tests
Requires-Dist: tifffile
Requires-Dist: numpy
Requires-Dist: scipy
Requires-Dist: imageio
Provides-Extra: io
Requires-Dist: h5py; extra == 'io'
Provides-Extra: plot
Requires-Dist: matplotlib; extra == 'plot'
Provides-Extra: tests
Requires-Dist: pytest; extra == 'tests'
Requires-Dist: coveralls; extra == 'tests'
Requires-Dist: flake8; extra == 'tests'
Requires-Dist: mypy; extra == 'tests'
